pytaipit/__init__.py
pytaipit/__main__.py
pytaipit/_version.py
pytaipit/api.py
pytaipit/auth.py
pytaipit/cli.py
pytaipit/const.py
pytaipit/exceptions.py
pytaipit/helpers.py
pytaipit/py.typed
pytaipit-1.1.0.dist-info/LICENSE
pytaipit-1.1.0.dist-info/METADATA
pytaipit-1.1.0.dist-info/WHEEL
pytaipit-1.1.0.dist-info/entry_points.txt
pytaipit-1.1.0.dist-info/top_level.txt
pytaipit-1.1.0.dist-info/RECORD
