Metadata-Version: 2.1
Name: pytaipit
Version: 1.1.0
Summary: Python API For Taipit Cloud Meters
Author: LizardSystems
License: MIT License
Project-URL: Home, https://github.com/lizardsystems/pytaipit
Project-URL: Repository, https://github.com/lizardsystems/pytaipit
Project-URL: Documentation, https://github.com/lizardsystems/pytaipit
Project-URL: Bug Tracker, https://github.com/lizardsystems/pytaipit/issues
Project-URL: Changelog, https://github.com/lizardsystems/pytaipit/blob/master/CHANGELOG.md
Keywords: taipit,neva,wi-fi,electricity meter
Platform: any
Classifier: Development Status :: 5 - Production/Stable
Classifier: License :: OSI Approved :: MIT License
Classifier: Intended Audience :: Developers
Classifier: Operating System :: OS Independent
Classifier: Programming Language :: Python
Classifier: Programming Language :: Python :: 3
Classifier: Programming Language :: Python :: 3.9
Classifier: Programming Language :: Python :: 3.10
Classifier: Programming Language :: Python :: 3.11
Classifier: Programming Language :: Python :: 3 :: Only
Classifier: Typing :: Typed
Requires-Python: >=3.9.0
License-File: LICENSE
Requires-Dist: requests
